BiVFM/__init__.py
BiVFM/config_transfer.py
BiVFM/feature_engineering.py
BiVFM/func.py
BiVFM/model.py
BiVFM/olga_func.py
BiVFM/train_func.py
BiVFM_Fleet-1.0.0.dist-info/License
BiVFM_Fleet-1.0.0.dist-info/METADATA
BiVFM_Fleet-1.0.0.dist-info/WHEEL
BiVFM_Fleet-1.0.0.dist-info/top_level.txt
BiVFM_Fleet-1.0.0.dist-info/RECORD
