Metadata-Version: 2.1
Name: BiVFM-Fleet
Version: 1.0.0
Summary: Paper: A Bi-Model Driven Transient Multiphase Virtual Flow Metering Paradigm for Arbitrary Well Patterns Based on the Mechanism Model and Data-Driven Model
Home-page: https://github.com/mmmahhhhe/BiVFM-Fleet
Author: He Ma
Author-email: mahepetroleum@163.com
Maintainer: He Ma
Maintainer-email: mahepetroleum@163.com
License: MIT License
Platform: all
Classifier: Development Status :: 3 - Alpha
Classifier: Intended Audience :: Developers
Classifier: Topic :: Software Development :: Build Tools
Classifier: License :: OSI Approved :: MIT License
Classifier: Programming Language :: Python :: 3
Requires-Python: >=3.9
License-File: License
